Workbook

Sheet Account GTM (Plan) Kubota
A1: 2026 ACCOUNT GO TO MARKET PLAN FOR: Kubota Credit Corporation
B2: Account Owner | C2: Diana Stevens
B3: Link to Acct in CRM: | C3: Dynamics 365 - Kafka POC Data Migration | H3: 62 | J3: 252
C4: 2025 Revenue | D4: 2025 Gross Profit | E4: 2025 GM | F4: Q4 2025 Revenue | G4: Q4 2025 GP | H4: Q4 2025 GM | I4: Q4 2025 Daily Revenue | J4: Current ARR
B5: ACCOUNT: Kubota Credit Corporation | C5: 0 | D5: =C5*E5 -> 0 | F5: 50000 | G5: =F5*H5 -> 19000 | H5: 0.38 | I5: =F5/H3 -> 806.45161 | J5: =I5*J3 -> 203225.81
B7: ICP Potential | C7: ='Account 9 Box'!F124 -> 3.4 | F7: 2025 Objectives Accomplished
B8: ICP Realized | C8: ='Account 9 Box'!F131 -> -4
B9: ICP State | C9: {=_xlfn.IFS('Account 9 Box'!B134 <-1.67,IF('Account 9 Box'!C134 <-1.67,"LIMITED",IF('Account 9 Box'!C134 < 1.67,"SOLID","SIGNIFICANT")),'Account 9 Box'!B134 < 1.67,IF('Account 9 Box'!C134 <-1.67,"CONSTRAINED",IF('Account 9 Box'!C134 < 1.67,"CORE","POISED")),TRUE(),IF('Account 9 Box'!C134 <-1.67,"CAPPED",IF('Account 9 Box'!C134 < 1.67,"STEADY","IDEAL")))} -> SIGNIFICANT
B11: Current Team | C11: Number | D11: Average Rate USD
B12: US/CAN | C12: 0 | D12: 0
B13: LATAM | C13: 0 | D13: 0
B14: ASIA | C14: 0 | D14: 0
C15: =SUM(C12:C14) -> 0 | D15: =((D12*C12)+(D13*C13)+(D14*C14))/C15 -> #DIV/0!
B17: ACCOUNT SUMMARY | C17: Current Status
B18: OVERALL | C18: =IF(C20="Behind","Behind",IF(AND(C20="On Track",C27="On Track"),"On Track",IF(AND(C20="On Track",OR(C27="Lagging",C27="Behind")),"Lagging",IF(AND(C20="Lagging",C27="Lagging"),"Lagging",IF(AND(C20="Lagging",C27="Behind"),"Lagging",IF(AND(C20="Lagging",C27="On Track"),"Lagging",IF(AND(C20="Behind",C27="Behind"),"Behind",""))))))) -> Behind
B20: OBJECTIVES | C20: {=IF(SUMPRODUCT((A21:A26="!")*(C21:C26="Behind"))>0,"Behind",IF(SUMPRODUCT((A21:A26="!")*(C21:C26="Lagging"))>0,"Lagging",IF(SUMPRODUCT((A21:A26="!")*(C21:C26="On Track"))=SUMPRODUCT((A21:A26="!")*(C21:C26<>"")),"On Track","")))} -> Behind
A21: =A37 -> ! | B21: =B37 -> 2026 Revenue (YTD) Goal | C21: =C49 -> Behind
A22: =A38 -> ! | B22: =B38 -> 2026 Quarterly Revenue Goal | C22: {=_xlfn.LET( _xlpm.today, TODAY(), _xlpm.m, MONTH(_xlpm.today), _xlpm.decActual, O51, _xlpm.effM, IF( _xlpm.m=1, IF(_xlpm.decActual<>"",12,1), IF( _xlpm.m=12, IF(_xlpm.decActual<>"",12,11), MAX(1,_xlpm.m-1) ) ), _xlpm.q, INT((_xlpm.effM-1)/3)+1, _xlpm.qStart, (_xlpm.q-1)*3+1, _xlpm.monthsDone, MAX(0, _xlpm.effM - _xlpm.qStart + 1), _xlpm.actualsRow, D51:O51, _xlpm.qGoals, D38:G38, IF( AND(_xlpm.m=1, _xlpm.decActual=""), "On Track", _xlfn.LET( _xlpm.actualsqtd, IF( _xlpm.monthsDone=0, 0, SUM( INDEX(_xlpm.actualsRow,1,_xlpm.qStart): INDEX(_xlpm.actualsRow,1,_xlpm.qStart+_xlpm.monthsDone-1) ) ), _xlpm.goalq, INDEX(_xlpm.qGoals,1,_xlpm.q), _xlpm.goalqtd, _xlpm.goalq * _xlpm.monthsDone / 3, _xlpm.ratio, IF(OR(_xlpm.goalqtd=0, _xlpm.monthsDone=0), 1, _xlpm.actualsqtd / _xlpm.goalqtd), IF(_xlpm.ratio<0.85,"Behind",IF(_xlpm.ratio<1,"Lagging","On Track")) ) ) )} -> Behind
A23: =A39 -> ! | B23: =B39 -> 2026 GM Goal | C23: =C55 -> Behind
A24: =A40 -> ! | B24: =B40 -> 2026 Quarterly GP Goal | C24: {=_xlfn.LET( _xlpm.today, TODAY(), _xlpm.m, MONTH(_xlpm.today), _xlpm.decActual, O58, _xlpm.effM, IF( _xlpm.m=1, IF(_xlpm.decActual<>"",12,1), IF( _xlpm.m=12, IF(_xlpm.decActual<>"",12,11), MAX(1,_xlpm.m-1) ) ), _xlpm.q, INT((_xlpm.effM-1)/3)+1, _xlpm.qStart, (_xlpm.q-1)*3+1, _xlpm.monthsDone, MAX(0, _xlpm.effM - _xlpm.qStart + 1), _xlpm.actualsRow, D58:O58, _xlpm.qGoals, D40:G40, IF( AND(_xlpm.m=1, _xlpm.decActual=""), "On Track", _xlfn.LET( _xlpm.actualsqtd, IF( _xlpm.monthsDone=0, 0, SUM( INDEX(_xlpm.actualsRow,1,_xlpm.qStart): INDEX(_xlpm.actualsRow,1,_xlpm.qStart+_xlpm.monthsDone-1) ) ), _xlpm.goalq, INDEX(_xlpm.qGoals,1,_xlpm.q), _xlpm.goalqtd, _xlpm.goalq * _xlpm.monthsDone / 3, _xlpm.ratio, IF(OR(_xlpm.goalqtd=0, _xlpm.monthsDone=0), 1, _xlpm.actualsqtd / _xlpm.goalqtd), IF(_xlpm.ratio<0.85,"Behind",IF(_xlpm.ratio<1,"Lagging","On Track")) ) ) )} -> Behind
A25: =A41 -> 2nd | B25: =B41 -> OBJ: Establish Kubota as reference account for financial services vertical | C25: =C62 -> Behind
A26: =A42 -> 2nd | B26: =B42 -> OBJ: Expand relationship map — connect with VP Engineering & Data teams | C26: =C66 -> Behind
B27: KEY ACTIVITES | C27: {=IF(SUMPRODUCT((A28:A33="!")*(C28:C33=0))>0,"Behind",IF(SUMPRODUCT((A28:A33="!")*(C28:C33="Behind"))>0,"Behind",IF(SUMPRODUCT((A28:A33="!")*(C28:C33="Lagging"))>0,"Lagging",IF(SUMPRODUCT((A28:A33="!")*((C28:C33="On Track")+(C28:C33="Complete")))>0,"On Track",""))))} -> Behind
B28: =B52 -> ACT: Close Kafka POC ($50K) — CDC proof-of-concept with Confluent | C28: =C52 -> Behind
B29: =B53 -> ACT: Expand to Phase 2 — Event-driven architecture & Flink processing | C29: =C53 -> Behind
A30: ! | B30: =B72 -> Team Quick Reviews Status | C30: =C72 -> 0
A31: ! | B31: =B79 -> Account Review / QBR (In Person with Sr. Exec) Status | C31: =C79 -> 0
B32: =B84 -> (IF Enterprise Top 10 ) Quarterly President In Person Status | C32: =C84 -> 0
B36: Account Objective (What) | C36: Year End Metric | D36: Q1 Metric | E36: Q2 Metric | F36: Q3 Metric | G36: Q4 Metric | H36: 2027 Forecast | I36: NOTES
A37: ! | B37: 2026 Revenue (YTD) Goal | C37: 150000 | D37: =D38 -> 31500 | E37: =E38+D37 -> 66000 | F37: =F38+E37 -> 106500 | G37: =G38+F37 -> 150000 | H37: 400000
A38: ! | B38: 2026 Quarterly Revenue Goal | D38: =$C$37*0.21 -> 31500 | E38: =$C$37*0.23 -> 34500 | F38: =$C$37*0.27 -> 40500 | G38: =$C$37*0.29 -> 43500 | I38: Account to have growth momentum at end of year
A39: ! | B39: 2026 GM Goal | C39: 0.38 | D39: =$C$39 -> 0.38 | E39: =$C$39 -> 0.38 | F39: =$C$39 -> 0.38 | G39: =$C$39 -> 0.38
A40: ! | B40: 2026 Quarterly GP Goal | D40: =D38*D39 -> 11970 | E40: =E38*E39 -> 13110 | F40: =F38*F39 -> 15390 | G40: =G38*G39 -> 16530
A41: 2nd | B41: =B62 -> OBJ: Establish Kubota as reference account for financial services vertical
A42: 2nd | B42: =B66 -> OBJ: Expand relationship map — connect with VP Engineering & Data teams
A43: 2nd
B48: Key Activities (How) | C48: Current Status | D48: 46023 | E48: =EDATE(D48,1) -> 46054 | F48: =EDATE(E48,1) -> 46082 | G48: =EDATE(F48,1) -> 46113 | H48: =EDATE(G48,1) -> 46143 | I48: =EDATE(H48,1) -> 46174 | J48: =EDATE(I48,1) -> 46204 | K48: =EDATE(J48,1) -> 46235 | L48: =EDATE(K48,1) -> 46266 | ... O48: =EDATE(N48,1) -> 46357 | P48: NOTES
A49: ! | B49: OBJ: 2026 Revenue $150K / Q4 Run-Rate for $400K in 2027 | C49: =IF(ISBLANK(C51),"",IF(C51>=C50,"On Track",IF(C51/C50>=0.85,"Lagging","Behind"))) -> Behind | D49: =IF(ISBLANK(D51),"",IF(D51>=D50,"On Track",IF(D51/D50>=0.51,"Lagging","Behind"))) | E49: =IF(ISBLANK(E51),"",IF(E51>=E50,"On Track",IF(E51/E50>=0.51,"Lagging","Behind"))) | F49: =IF(ISBLANK(F51),"",IF(F51>=F50,"On Track",IF(F51/F50>=0.51,"Lagging","Behind"))) | G49: =IF(ISBLANK(G51),"",IF(G51>=G50,"On Track",IF(G51/G50>=0.51,"Lagging","Behind"))) | H49: =IF(ISBLANK(H51),"",IF(H51>=H50,"On Track",IF(H51/H50>=0.51,"Lagging","Behind"))) | I49: =IF(ISBLANK(I51),"",IF(I51>=I50,"On Track",IF(I51/I50>=0.51,"Lagging","Behind"))) | J49: =IF(ISBLANK(J51),"",IF(J51>=J50,"On Track",IF(J51/J50>=0.51,"Lagging","Behind"))) | K49: =IF(ISBLANK(K51),"",IF(K51>=K50,"On Track",IF(K51/K50>=0.51,"Lagging","Behind"))) | ... O49: =IF(ISBLANK(O51),"",IF(O51>=O50,"On Track",IF(O51/O50>=0.51,"Lagging","Behind")))
B50: Target (YTD) | C50: {=SUMPRODUCT((D$48:O$48<=EDATE(TODAY(),-1))*(D50:O50))} -> 21000 | D50: =$D38/3 -> 10500 | E50: =$D38/3 -> 10500 | F50: =$D38/3 -> 10500 | G50: =$E38/3 -> 11500 | H50: =$E38/3 -> 11500 | I50: =$E38/3 -> 11500 | J50: =$F38/3 -> 13500 | K50: =$F38/3 -> 13500 | L50: =$F38/3 -> 13500 | M50: =$G38/3 -> 14500 | N50: =$G38/3 -> 14500 | O50: =$G38/3 -> 14500
B51: Actual (YTD) | C51: {=SUMPRODUCT((D$48:O$48<=EDATE(TODAY(),-1))*(D51:O51))} -> 0
B52: ACT: Close Kafka POC ($50K) — CDC proof-of-concept with Confluent | C52: {=IF(MONTH(TODAY())=1,$D52,_xlfn.LET(_xlpm.dates,$D$48:$O$48,_xlpm.values,$D52:$O52,_xlpm.matchCol,_xlfn.XMATCH(MONTH(TODAY()),MONTH(_xlpm.dates),0,1),_xlpm.val,INDEX(_xlpm.values,_xlpm.matchCol),_xlpm.result,IF(_xlpm.val<>"",_xlpm.val,INDEX(_xlpm.values,_xlpm.matchCol-1)),IF(_xlpm.result<>"",_xlpm.result,"Behind")))} -> Behind
B53: ACT: Expand to Phase 2 — Event-driven architecture & Flink processing | C53: {=IF(MONTH(TODAY())=1,$D53,_xlfn.LET(_xlpm.dates,$D$48:$O$48,_xlpm.values,$D53:$O53,_xlpm.matchCol,_xlfn.XMATCH(MONTH(TODAY()),MONTH(_xlpm.dates),0,1),_xlpm.val,INDEX(_xlpm.values,_xlpm.matchCol),_xlpm.result,IF(_xlpm.val<>"",_xlpm.val,INDEX(_xlpm.values,_xlpm.matchCol-1)),IF(_xlpm.result<>"",_xlpm.result,"Behind")))} -> Behind
B54: ACT: Introduce Microsoft Fabric play — 3-way deal with Confluent + MSFT | C54: {=IF(MONTH(TODAY())=1,$D54,_xlfn.LET(_xlpm.dates,$D$48:$O$48,_xlpm.values,$D54:$O54,_xlpm.matchCol,_xlfn.XMATCH(MONTH(TODAY()),MONTH(_xlpm.dates),0,1),_xlpm.val,INDEX(_xlpm.values,_xlpm.matchCol),_xlpm.result,IF(_xlpm.val<>"",_xlpm.val,INDEX(_xlpm.values,_xlpm.matchCol-1)),IF(_xlpm.result<>"",_xlpm.result,"Behind")))} -> Behind
A55: ! | B55: OBJ: 2026 GM of 38% | C55: =IF(ISBLANK(C58),"",IF(C58>=C57,"On Track",IF(C58/C57>=0.51,"Lagging","Behind"))) -> Behind | D55: =IF(ISBLANK(D58),"",IF(D58>=D57,"On Track",IF(D58/D57>=0.51,"Lagging","Behind"))) | E55: =IF(ISBLANK(E58),"",IF(E58>=E57,"On Track",IF(E58/E57>=0.51,"Lagging","Behind"))) | F55: =IF(ISBLANK(F58),"",IF(F58>=F57,"On Track",IF(F58/F57>=0.51,"Lagging","Behind"))) | G55: =IF(ISBLANK(G58),"",IF(G58>=G57,"On Track",IF(G58/G57>=0.51,"Lagging","Behind"))) | H55: =IF(ISBLANK(H58),"",IF(H58>=H57,"On Track",IF(H58/H57>=0.51,"Lagging","Behind"))) | I55: =IF(ISBLANK(I58),"",IF(I58>=I57,"On Track",IF(I58/I57>=0.51,"Lagging","Behind"))) | J55: =IF(ISBLANK(J58),"",IF(J58>=J57,"On Track",IF(J58/J57>=0.51,"Lagging","Behind"))) | ... O55: =IF(ISBLANK(O58),"",IF(O58>=O57,"On Track",IF(O58/O57>=0.51,"Lagging","Behind")))
B56: Actual GM | C56: =IFERROR(C58/C51,0) -> 0
B57: Target GP (YTD) | C57: {=SUMPRODUCT((D$48:O$48<=EDATE(TODAY(),-1))*(D57:O57))} -> 7980 | D57: =$D40/3 -> 3990 | E57: =$D40/3 -> 3990 | F57: =$D40/3 -> 3990 | G57: =($E39*$E38)/3 -> 4370 | H57: =($E39*$E38)/3 -> 4370 | I57: =($E39*$E38)/3 -> 4370 | J57: =($F39*$F38)/3 -> 5130 | K57: =($F39*$F38)/3 -> 5130 | L57: =($F39*$F38)/3 -> 5130 | M57: =($G39*$G38)/3 -> 5510 | N57: =($G39*$G38)/3 -> 5510 | O57: =($G39*$G38)/3 -> 5510
B58: Actual GP (YTD) | C58: {=SUMPRODUCT((D$48:O$48<=EDATE(TODAY(),-1))*(D58:O58))} -> 0
B59: ACT: Staff with senior data engineers (maintain 38%+ margin) | C59: {=IF(MONTH(TODAY())=1,$D59,_xlfn.LET(_xlpm.dates,$D$48:$O$48,_xlpm.values,$D59:$O59,_xlpm.matchCol,_xlfn.XMATCH(MONTH(TODAY()),MONTH(_xlpm.dates),0,1),_xlpm.val,INDEX(_xlpm.values,_xlpm.matchCol),_xlpm.result,IF(_xlpm.val<>"",_xlpm.val,INDEX(_xlpm.values,_xlpm.matchCol-1)),IF(_xlpm.result<>"",_xlpm.result,"Behind")))} -> Behind
B60: ACT: Leverage Confluent partnership for co-delivery / shared resources | C60: {=IF(MONTH(TODAY())=1,$D60,_xlfn.LET(_xlpm.dates,$D$48:$O$48,_xlpm.values,$D60:$O60,_xlpm.matchCol,_xlfn.XMATCH(MONTH(TODAY()),MONTH(_xlpm.dates),0,1),_xlpm.val,INDEX(_xlpm.values,_xlpm.matchCol),_xlpm.result,IF(_xlpm.val<>"",_xlpm.val,INDEX(_xlpm.values,_xlpm.matchCol-1)),IF(_xlpm.result<>"",_xlpm.result,"Behind")))} -> Behind
B61: ACT: Establish fixed-price SOW for Phase 2 to protect margin | C61: {=IF(MONTH(TODAY())=1,$D61,_xlfn.LET(_xlpm.dates,$D$48:$O$48,_xlpm.values,$D61:$O61,_xlpm.matchCol,_xlfn.XMATCH(MONTH(TODAY()),MONTH(_xlpm.dates),0,1),_xlpm.val,INDEX(_xlpm.values,_xlpm.matchCol),_xlpm.result,IF(_xlpm.val<>"",_xlpm.val,INDEX(_xlpm.values,_xlpm.matchCol-1)),IF(_xlpm.result<>"",_xlpm.result,"Behind")))} -> Behind
A62: 2nd | B62: OBJ: Establish Kubota as reference account for financial services vertical | C62: {=IF(MONTH(TODAY())=1,$D62,_xlfn.LET(_xlpm.dates,$D$48:$O$48,_xlpm.values,$D62:$O62,_xlpm.matchCol,_xlfn.XMATCH(MONTH(TODAY()),MONTH(_xlpm.dates),0,1),_xlpm.val,INDEX(_xlpm.values,_xlpm.matchCol),_xlpm.result,IF(_xlpm.val<>"",_xlpm.val,INDEX(_xlpm.values,_xlpm.matchCol-1)),IF(_xlpm.result<>"",_xlpm.result,"Behind")))} -> Behind
B63: ACT: Deliver POC on time with measurable CDC latency improvements | C63: {=IF(MONTH(TODAY())=1,$D63,_xlfn.LET(_xlpm.dates,$D$48:$O$48,_xlpm.values,$D63:$O63,_xlpm.matchCol,_xlfn.XMATCH(MONTH(TODAY()),MONTH(_xlpm.dates),0,1),_xlpm.val,INDEX(_xlpm.values,_xlpm.matchCol),_xlpm.result,IF(_xlpm.val<>"",_xlpm.val,INDEX(_xlpm.values,_xlpm.matchCol-1)),IF(_xlpm.result<>"",_xlpm.result,"Behind")))} -> Behind
B64: ACT: Get executive sponsor (David Costa, CIO) bought in on Phase 2 roadmap | C64: {=IF(MONTH(TODAY())=1,$D64,_xlfn.LET(_xlpm.dates,$D$48:$O$48,_xlpm.values,$D64:$O64,_xlpm.matchCol,_xlfn.XMATCH(MONTH(TODAY()),MONTH(_xlpm.dates),0,1),_xlpm.val,INDEX(_xlpm.values,_xlpm.matchCol),_xlpm.result,IF(_xlpm.val<>"",_xlpm.val,INDEX(_xlpm.values,_xlpm.matchCol-1)),IF(_xlpm.result<>"",_xlpm.result,"Behind")))} -> Behind
B65: ACT: Publish internal case study for Confluent + Kafka delivery capability | C65: {=IF(MONTH(TODAY())=1,$D65,_xlfn.LET(_xlpm.dates,$D$48:$O$48,_xlpm.values,$D65:$O65,_xlpm.matchCol,_xlfn.XMATCH(MONTH(TODAY()),MONTH(_xlpm.dates),0,1),_xlpm.val,INDEX(_xlpm.values,_xlpm.matchCol),_xlpm.result,IF(_xlpm.val<>"",_xlpm.val,INDEX(_xlpm.values,_xlpm.matchCol-1)),IF(_xlpm.result<>"",_xlpm.result,"Behind")))} -> Behind
A66: 2nd | B66: OBJ: Expand relationship map — connect with VP Engineering & Data teams | C66: {=IF(MONTH(TODAY())=1,$D66,_xlfn.LET(_xlpm.dates,$D$48:$O$48,_xlpm.values,$D66:$O66,_xlpm.matchCol,_xlfn.XMATCH(MONTH(TODAY()),MONTH(_xlpm.dates),0,1),_xlpm.val,INDEX(_xlpm.values,_xlpm.matchCol),_xlpm.result,IF(_xlpm.val<>"",_xlpm.val,INDEX(_xlpm.values,_xlpm.matchCol-1)),IF(_xlpm.result<>"",_xlpm.result,"Behind")))} -> Behind
B67: ACT: Map Kubota org chart beyond IT — find data team leads | C67: {=IF(MONTH(TODAY())=1,$D67,_xlfn.LET(_xlpm.dates,$D$48:$O$48,_xlpm.values,$D67:$O67,_xlpm.matchCol,_xlfn.XMATCH(MONTH(TODAY()),MONTH(_xlpm.dates),0,1),_xlpm.val,INDEX(_xlpm.values,_xlpm.matchCol),_xlpm.result,IF(_xlpm.val<>"",_xlpm.val,INDEX(_xlpm.values,_xlpm.matchCol-1)),IF(_xlpm.result<>"",_xlpm.result,"Behind")))} -> Behind
B68: ACT: Schedule intro meeting with Improving leadership (Scott McMichael) | C68: {=IF(MONTH(TODAY())=1,$D68,_xlfn.LET(_xlpm.dates,$D$48:$O$48,_xlpm.values,$D68:$O68,_xlpm.matchCol,_xlfn.XMATCH(MONTH(TODAY()),MONTH(_xlpm.dates),0,1),_xlpm.val,INDEX(_xlpm.values,_xlpm.matchCol),_xlpm.result,IF(_xlpm.val<>"",_xlpm.val,INDEX(_xlpm.values,_xlpm.matchCol-1)),IF(_xlpm.result<>"",_xlpm.result,"Behind")))} -> Behind
B69: ACT: Leverage Danny Chanyalew relationship for internal champion building | C69: {=IF(MONTH(TODAY())=1,$D69,_xlfn.LET(_xlpm.dates,$D$48:$O$48,_xlpm.values,$D69:$O69,_xlpm.matchCol,_xlfn.XMATCH(MONTH(TODAY()),MONTH(_xlpm.dates),0,1),_xlpm.val,INDEX(_xlpm.values,_xlpm.matchCol),_xlpm.result,IF(_xlpm.val<>"",_xlpm.val,INDEX(_xlpm.values,_xlpm.matchCol-1)),IF(_xlpm.result<>"",_xlpm.result,"Behind")))} -> Behind
B71: Account Requirements | C71: Current Status | D71: 46023 | E71: =EDATE(D71,1) -> 46054 | F71: =EDATE(E71,1) -> 46082 | G71: =EDATE(F71,1) -> 46113 | H71: =EDATE(G71,1) -> 46143 | I71: =EDATE(H71,1) -> 46174 | J71: =EDATE(I71,1) -> 46204 | K71: =EDATE(J71,1) -> 46235 | L71: =EDATE(K71,1) -> 46266 | ... O71: =EDATE(N71,1) -> 46357 | P71: NOTES
B72: Team Quick Reviews Status | P72: 2 per year per team member
B74: Quick Reviews Scheduled (Date) | P74: Scheduled before by 1 Jan OR 1 July)
B75: Quick Reviews Conducted (Date)
B76: QRs Documented (Date)
B77: QRs Reviewed (Date)
B78: QRs Discussed (Date) | P78: By 30 June or 31 Dec
B79: Account Review / QBR (In Person with Sr. Exec) Status | P79: 2 per year in Person including Improving Senior Executive (President, CEO, etc if in the top 10)
B81: AR Scheduled (Date) | P81: Scheduled before by 1 Jan OR 1 July)
B82: AR Conducted (Date)
B83: AR Documented (Date) | P83: By 30 June or 31 Dec
B84: (IF Enterprise Top 10 ) Quarterly President In Person Status | P84: Exeptions made ONLY by MD; Can double up with AR
B85: QBR Date

Sheet Acct Info & Act - Kubota
A1: ='Account GTM (Plan) Kubota'!A1 -> 2026 ACCOUNT GO TO MARKET PLAN FOR: Kubota Credit Corporation | I1: <Add Customer's Logo here>
B2: Link to Acct in CRM: | C2: ='Account GTM (Plan) Kubota'!C3 -> Dynamics 365 - Kafka POC Data Migration
B4: GENERAL ACCOUNT INFORMATION
B5: Account or Prospect? | C5: Prospect | E5: Annual Revenue: | F5: $20.46B (parent Kubota Corp) | H5: Number of Employees: | I5: ~19 (KCC) / 50,000+ (parent)
B6: Customer Location: | C6: 1000 Kubota Dr, Grapevine, TX 76051 | E6: Enterprise (s)/Office(s): | F6: Grapevine TX (HQ), Torrance CA | H6: Industry: | I6: Financial Services — Equipment Financing
B7: Lead Source: | C7: Partner Referral — Rob Ogbah / Confluent | E7: Initial Contract: | H7: Average Contract Duration:
B8: Services (Primary): | C8: Data Streaming, CDC Implementation, Event-Driven Architecture, Kafka/Confluent, Microsoft Fabric
B10: ACCOUNT BUSINESS OVERVIEW AND OBJECTIVES
B11: Kubota Credit Corporation (KCC) is the captive financing arm of Kubota Corporation, providing retail financing, wholesale financing, and leasing for Kubota equipment dealers and customers across North America. KCC operates a monolithic loan origination system they are looking to modernize with event-driven architecture using Change Data Capture (CDC) and Confluent Cloud. Immediate opportunity: $50K Kafka POC for data migration, with expansion into Flink stream processing, Microsoft Fabric integration, and AI/automation agents. David O'Hara has prior relationship with Danny Chanyalew from HDFS (Hitachi Dealer Financial Services) days.
B12: KEY CONTACTS
B13: Name | D13: Title | E13: Buyer Type | F13: Influence (H/M/L) | G13: Relationship | H13: Actions / Notes
B14: David Costa | D14: CIO | E14: Economic | F14: H | G14: New — intro via Confluent | H14: Executive sponsor. Schedule 1:1 for IT vision and budget cycle.
B15: Danny Chanyalew | D15: IT (Role TBD) | E15: Technical | F15: H | G15: Warm — prior HDFS relationship with David O'Hara | H15: Internal champion. Nurture actively.
B16: Eric Gregory | D16: IT (Role TBD) | E16: Technical | F16: M | G16: New — intro via Confluent | H16: Technical evaluator on POC. Ensure he sees value.
B17: Rob Ogbah (Confluent) | D17: Strategic Account Executive | E17: Influencer/Partner | F17: H | G17: Strong — active partner referral | H17: Co-sell partner. Keep aligned on POC scope and expansion.
B25: COMPETITORS
B26: Competitor | D26: Notes (Number of Consultants, Services, Rates, etc.)
B27: Accenture / Deloitte | D27: Large SIs at Kubota Corp parent level. Slower, expensive. Our edge: speed, specialization, local.
B28: Slalom | D28: DFW presence, data/cloud focus. Differentiate on Confluent partnership depth.
B35: CURRENT TECH STACK
B36: Type | C36: Existing Solution | E36: Vendor | F36: Satisfaction | G36: Actions / Opportunities
B37: Cloud Platform | C37: Microsoft | G37: Confirm cloud provider during POC discovery. Microsoft Fabric play if Azure.
B38: ERP - Mainframe​ | C38: Monolithic loan origination system (legacy) | G38: Core modernization target. CDC to decouple from monolith.
B39: Modern APIs​ | C39: Evaluating event-driven architecture | G39: Confluent Cloud + Kafka Connect for CDC. Flink for stream processing.
B40: Data​ | C40: Legacy batch processing pipelines | G40: Migrate to real-time streaming. Microsoft Fabric for analytics layer.
B41: AI Solutions | C41: Early stage / evaluating | G41: AI agents for loan processing automation — Phase 3+ opportunity.
B42: Development​ | C42: Java/enterprise stack | G42: Microservices architecture consulting opportunity.
B43: Training/Coaching​
B44: Global Delivery
B45: PARTNERSHIP-RELATED ACTIVITIES
B46: Partnership | C46: Does Client have Tech? | D46: Rep Name | F46: Relationship w/ Rep | G46: Deals Registered? | H46: Actions | J46: Due Date / Completion Date
B47: AWS
B48: Confluent | C48: Yes — Confluent Cloud (evaluating) | D48: Rob Ogbah | F48: Strong — active co-sell | G48: In progress — Kafka POC | H48: Co-deliver POC. Register deal. Explore Flink expansion.
B49: Databricks
B50: Google
B51: Microsoft | C51: Yes | D51: No rep - confirmed | G51: No | H51: Reach out to PLSR about Fabric/Azure deal
B52: SAP
B53: Snowflake
B55: OFFERING-RELATED ACTIVITIES
B56: Offering (Samples - Add others as appropriate) | D56: Does this apply to Client? | E56: Have we discussed? | F56: Actions | J56: Due / Completion Date
B57: Code Explorer | D57: Yes
B58: Platform Migration (AWS, GCP, Azure) | D58: Yes | E58: Not yet | F58: Azure migration mentioned in Discovery
B59: Data | D59: Yes | E59: Yes | F59: Kafka. CDC, Confluent Cloud, Flink, Microsoft Fabric.
B60: Global Delivery | D60: Possibly | E60: Not yet | F60: Signficant alignment with LATAM prior work
B61: Training | D61: Yes | E61: Not yet | F61: Confluent/Kafka training for Kubota internal teams post-POC.
B62: Managed Services | D62: Possibly | E62: Not yet | F62: Managed Kafka/streaming services after platform is built. Phase 3+.
B66: OTHER ACTIVITIES
B67: Activity | D67: Applies? | E67: Discussed? | F67: Actions | G67: Actions | J67: Due / Completion Date
B76: COMPLETED ACTIVITIES
B77: Item | G77: Actions | J77: Completed Date

Sheet Account 9 Box
A22: Account
A23: Potential
A24: Best case, what do you think that annual IT services spend could be at this client? | H24: 5000000
A25: What do you think is the maximum average gross margin could be this client? | H25: 0.45
A26: Is the client located in an area where Improving has an office? | H26: Y
A27: Realized
A28: What is the TTM revenue at this client? | H28: 0
A29: What is the TTM gross margin at this client? | H29: 0
A30: Does our delivery lead or biz dev executive live in the same place as the client buyer? | H30: Y
A120: Potential Calculations | U120: Potential Weighted Value
A121: Geography | B121: Value | C121: =IF(H26="Y", 5, 0) -> 5 | D121: Weighted Value: | F121: =C121*$V$121 -> 0.5 | U121: Geo | V121: 0.1
A122: Revenue | B122: Value | C122: {=_xlfn.IFS(H24<=$U$126,$V$126, H24<=$U$127,$V$127, H24<=$U$128,$V$128, H24<=$U$129, $V$129, H24<=$U$130, $V$130, H24>=$U$136,$V$136,H24>=$U$135,$V$135,H24>=$U$134,$V$134,H24>=$U$133,$V$133,H24>=$U$132,$V$132, H24>0,$V$131)} -> 3 | D122: Weighted Value: | F122: =C122*$V$122 -> 2.1 | U122: Revenue | V122: 0.7
A123: Gross Margin | B123: Value | C123: {=_xlfn.IFS(H25<$X$126,$Y$126, H25>=$X$136,$Y$136,H25>=$X$135,$Y$135,H25>=$X$134,$Y$134,H25>=$X$133,$Y$133,H25>=$X$132,$Y$132, H25>=$X$131,$Y$131,H25>=$X$130,$Y$130,H25>=$X$129,$Y$129,H25>=$X$128,$Y$128,H25>=$X$127,$Y$127 )} -> 4 | D123: Weighted Value: | F123: =C123*$V$123 -> 0.8 | U123: GM | V123: 0.2
A124: Potential | F124: =SUM(F121:F123) -> 3.4
U125: Revnue: | V125: Score | X125: Gross Margin | Y125: Score
U126: 200000 | V126: -5 | X126: 0.2 | Y126: -5
A127: Realized Calculations | U127: 300000 | V127: -4 | X127: 0.2 | Y127: -4
A128: Geography | B128: Value | C128: =IF(H30="Y", 5, 0) -> 5 | D128: Weighted Value: | F128: =C128*$V$121 -> 0.5 | U128: 400000 | V128: -3 | X128: 0.24 | Y128: -3
A129: Revenue | B129: Value | C129: =( H28/(IF(H24>=U136,U136,H24) )*V139+V138) -> -5 | D129: Weighted Value: | F129: =C129*$V$122 -> -3.5 | U129: 500000 | V129: -2 | X129: 0.27 | Y129: -2
A130: Gross Margin | B130: Value | C130: {=_xlfn.IFS(H29>=X136,Y136,H29<X126,Y126,H29>0,(H29-X126)/(H25-X126)*V139+V138)} -> -5 | D130: Weighted Value: | F130: =C130*$V$123 -> -1 | U130: 750000 | V130: -1 | X130: 0.3 | Y130: -1
A131: Realized | F131: =SUM(F128:F130) -> -4 | U131: 1000000 | V131: 0 | X131: 0.32 | Y131: 0
U132: 1000000 | V132: 1 | X132: 0.34 | Y132: 1
B133: X | C133: Y | U133: 2000000 | V133: 2 | X133: 0.37 | Y133: 2
B134: =F131 -> -4 | C134: =F124 -> 3.4 | U134: 5000000 | V134: 3 | X134: 0.4 | Y134: 3
U135: 10000000 | V135: 4 | X135: 0.45 | Y135: 4
U136: 20000000 | V136: 5 | X136: 0.5 | Y136: 5
U138: Measurement Low | V138: -5
A139: SIGNIFICANT | U139: Revenue Scale | V139: 10
A140: POISED
A141: IDEAL
A142: SOLID
A143: CORE
A144: STEADY
A145: LIMITED
A146: CONSTRAINED
A147: CAPPED

Sheet Acct Goals - Medica
A1: 2025 ACCOUNT GO TO MARKET PLAN FOR: MEDICA
B2: Link to Acct in CRM: | C2: Medica Account
B4: GENERAL ACCOUNT INFORMATION
B5: Account or Prospect? | C5: Account | E5: Annual Revenue: | F5: 3.8 Billion | H5: Number of Employees: | I5: 4500
B6: Customer Location: | C6: Minnetonka, MN | E6: Enterprise (s)/Office(s): | F6: Minnesota | H6: Industry: | I6: Heakth Insurance
B7: Lead Source: | C7: Matt knows Keith Tanski | E7: Initial Contract: | F7: 45658 | H7: Average Contract Duration: | I7: 1 Year
B8: Active Consultants (#): | C8: 7 | E8: Peak Consultants (#): | F8: 7 | H8: Ave Project Gross Margin %: | I8: 0.566
B9: Services (Primary): | C9: Nearshore - Power BI
B11: ACCOUNT SPECIFIC OBJECTIVES (5 Minimum)
B12: List Your Account Objectives (Start with overall goal of 2026) | F12: Status (Not Started, In Process, On Hold, or Complete) | G12: Actions Required to Achieve | J12: Due / Completion Date
B13: Overall Goal: The primary goal is to expand from the initial project of updating the delivery framework to expanded work in applications, APIs, Data, and Platform Engineering | F13: In Process | G13: Programatic look at the account, engaging all services, partners, and delivery methodologies (Nearshore, Offshore) | J13: 46387
B14: Data: Land the Data Director role | F14: Complete | G14: SOW in flight, should be signed next week. Troy Forte | J14: 45962
B15: API: Land the API/Kafka work | F15: In Process | G15: RFI responded to on 10/24/25 | J15: 45992
B16: Platform Engineering: Work with Cedric Dean to land platform engineering team | F16: In Process | G16: Initial meeting on 10/23/25 | J16: 46052
B17: Delivery Framework: Expand team led by Mike Azocar | F17: In Process | G17: Big Delivery at the end of the year, grow relationship with the decision maker | J17: 46068
B18: Increase utilization of Nearshore and Offfshore | F18: In Process | G18: Work with Vishal and Iago to grow their teams | J18: 45703
B19: Replace CapGemini as #1 PowerBI dashboard partner | F19: In Process | G19: Continue working with Andy and Penny to execute work of 10 dashboards | J19: 46082
B20: Land one engagement with a business unit (Not IT) | F20: Not Started | G20: Need to identify business leader and a specific need | J20: 46174
B21: Partner with Microsoft and receive funding | F21: Started | G21: I have identified the MSFT account manager | J21: 46143
B22: •Increase Account Score from 3.75 to 4.0 | J22: 46174
B25: KEY ACTIVITY METRICS (3 Minimum)
B26: Key Metric | F26: Status | G26: Actions Required to Achieve | J26: Due / Completion Date
B27: When is this quarter's QBR? (required) | J27: 46053
B28: Have you scheduled next quarter's QBR? (required - if yes, provide date) | J28: 46053
B29: Have you completed the Consultant Reviews for this 6 month period? (required) | J29: 46053
B30: Meet with MSFT, Snowflake, and Confluent Account Teams once per month | F30: Started | G30: This will require a specific meeting at Improving offices where we invite the partner and the Improving account team | J30: 46053
B31: Meet with Keith Tanski in person 6 times per year | F31: In Process | G31: Schedule with Keith's admin. Agenda developed. Delivery Director included | J31: 45992
B32: Reveive over $100k in Partner Funding | F32: In Process | G32: Wortk with the partner team to develop applications, manage to completion | J32: TBD
B33: Perform a QBR each quarter | F33: In Process | G33: Invite Medica IT Leadership, present overall status of projects | J33: 46023
B34: Invite and arrange trip to offshore or nearshore delivery center | F34: Not Started | G34: Invite Medica IT leadership to a delivery center, arrange travel | J34: 46174
B35: Onboard a second delivery director due to account demand | F35: In Process | G35: Generate enough business to justify a second delivery director | J35: 46174
B36: Maintain account margin of 50% | F36: In Process | G36: Current margin is 55% | J36: 46387
B39: PARTNERSHIP-RELATED ACTIVITIES
B40: Partnership | C40: Does Client have Tech? | D40: Rep Name | F40: Relationship w/ Rep | G40: Deals Registered? | H40: Actions | J40: Due / Completion Date
B41: AWS | C41: Yes | D41: TBD | F41: TBD | G41: None | H41: Intro meeting with AWS rep | J41: 46053
B42: Confluent | C42: Yes | D42: Tony Brinkhaus | F42: Strong | G42: Yes | H42: Close registered Conflunet Cloud deal | J42: 46053
B43: Databricks | C43: Yes | D43: David Kretsch | F43: Strong | G43: Yes | H43: Close Registered Databricks deal | J43: 46113
B44: Google | C44: Yes | D44: TBD | F44: TBD | G44: None | H44: Intro meeting with GCP rep | J44: 46113
B45: Microsoft | C45: Yes | D45: Bryan Haslip | F45: Aware | G45: Yes | H45: Continued conversations on consumption | J45: 46113
B46: SAP | C46: Unknown | D46: TBD | F46: TBD | G46: None | H46: Find rep (if one exists) | J46: 46113
B47: Snowflake | C47: Yes | D47: Mike Green | F47: Strong | G47: Yes | H47: Close Snowflake work with Iago | J47: 46113
B49: OFFERING-RELATED ACTIVITIES
B50: Offering | D50: Does this apply to Client? | F50: Have we discussed? | G50: Actions | J50: Due / Completion Date
B51: Code Explorer | D51: Yes | F51: No | G51: The current plan is to include CodeExplorer into the delivery methadology of the ongoing data work | J51: 46082
B52: Platform Migration (AWS, GCP, Azure) | D52: Yes | F52: Yes | G52: We are already engaged with the Platform Engineering team | J52: Complete
B53: Data | D53: Yes | F53: Yes | G53: Working with Aaron Strey and Mike Schlosser | J53: Complete
B54: Global Delivery | D54: Yes | F54: Yes | G54: Argentina engaged, 2 SOWs in flight for Pune | J54: Underway
B55: Training | D55: Yes | F55: Yes | G55: Training/Coaching with Mike Azocar | J55: Complete
B56: Managed Services | D56: Yes | F56: No | G56: This will be a part of the PowerBI deliverable (SOW to maintain) | J56: Not Started
B60: OTHER ACTIVITIES
B61: Activity | E61: Requires Asst From? | G61: Actions | J61: Due / Completion Date
B62: I would like to set up a healthcare payor conference with a speaker. Invite Medica, XH, BCBS-MN, UHG, Ucare | E62: Kristin Johnson and Steve Banks | G62: Need to identify a topic and/or speaker | J62: 46082
B63: Build upon the POC we are developing | E63: Nick Larson and Nick Spilman | G63: How do we leverage the work completed for the POC? | J63: TBD
B70: COMPLETED ACTIVITIES
B71: Item | G71: Actions | J71: Completed Date
B72: Landed Data Lead in Troy Forte | G72: Open Project | J72: 45968
B73: Respond to RFI | G73: Submited RFI response | J73: 45968

Sheet Acct Information - Medica
B1: GENERAL ACCOUNT INFORMATION
B2: Customer Name: | C2: ='Acct Goals - Medica'!C1 -> 0 | E2: Account or Prospect | F2: ='Acct Goals - Medica'!C5 -> Account | H2: Last Updated | I2: ='Acct Goals - Medica'!#REF! -> #REF!
B3: IDEAL CUSTOMER PROFILE CRITERIA
B4: Criteria | E4: Ranking | G4: Criteria | J4: Ranking
B5: Geographic Proximity (# miles) | E5: 4 | G5: Contract Compatability (<score>) | J5: -1
B6: Revenue Potential / Budget (~$X/year) | E6: 4 | G6: Level of Executive Contact (CIO, VP of Arch) | J6: 3
B7: Gross Margin (#%) | E7: 5 | G7: Service Alignment (<score>) | J7: 2
B8: Contract Duration (# months) | E8: 2 | G8: Cultural Alignment (<score>) | J8: 3
B9: Customer Profile Alignment: | D9: <Provide your view on how the client fits into the Improving "Ideal Customer Profile" - any concerns or specific areas to highlight?>
B11: KEY CONTACTS
B12: Name | D12: Title | F12: Influence (H/M/L) | G12: Relationship | H12: Actions / Notes
B13: Keith Tanski | D13: CIO | F13: High | G13: Very Strong | H13: Keith is our champion, consistently pushing business to Improving
B14: Aaron Strey | D14: VP of Data | F14: High | G14: Strong | H14: Aaron was a client at Optum, likes our consultants
B15: Mike Schlosser | D15: VP of A.I. | F15: Medium | G15: Medium | H15: Mike worked with us at Optum but was a teammeber, not a manager
B16: Chris Walter | D16: VP of Integration | F16: High | G16: Medium | H16: Chris is new to Improving but knows our reputation and is giving work
B17: Cedric Dean | D17: Lead Solution Architect | F17: Medium | G17: Medium | H17: Only 3 meetings but he seems to like us and next meeting we engage on work
B18: Andy Dybvig | D18: VP of Enterprise Analytics | F18: High | G18: Medium | H18: Nearshore team has already demonstrated we are amazing, keep growing
B19: Penny Tatman | D19: Sr. Director - Enterprise Analytics | F19: Medium | G19: Medium | H19: Nearshore team has already demonstrated we are amazing, keep growing
B20: Jane Ryan | D20: VP of Applications | F20: High | G20: Medium | H20: Mike Azocar working with Jane but I need to meet and strategize
A24: 8 | B24: COMPETITORS
B25: Competitor | D25: Notes (Number of Consultants, Services, Rates, etc.)
B26: CapGemini | D26: CapGemini is the primary IT services vendor to Medica. They are not considered to be high quality and the strategic direction at Medica is to move away.
B27: Perficient | D27: Perficient helped with the Digital transformation of Medica in 2024. This was part of the old CIO's plan. Perficient is being rolled out
B28: Slalom | D28: Slalom is working on SFDC work. Not engaged elsewhere
B29: Deloitte | D29: Deloitte is helping the COO and CMO with some business strategy work
B34: CURRENT TECH STACK
B35: Type | C35: Existing Solution | E35: Vendor | F35: Satisfaction | G35: Actions / Opportunities
B36: Cloud Platform | C36: MSFT Azure | E36: MSFT | F36: Very | G36: We are partnered with MSFT
B37: ERP - Mainframe​ | C37: IBM | E37: IBM | F37: ??? | G37: None
B38: Modern APIs​ | C38: MuleSoft | E38: SFDC | F38: Low | G38: We responded to the RFI. We are taking this work!
B39: Data​ | C39: Snowflake | E39: Snowflake | F39: Medium | G39: We responded to the RFI. We are taking this work!
B40: AI Solutions | C40: None/In Development | E40: None | G40: Get A.I. specalist at Medica
B41: Development​ | G41: Replace CapGemini
B42: Training/Coaching​ | C42: Improving | E42: Improving | F42: Medium | G42: Keep Mike Azocar in 2026
B43: Global Delivery | C43: CapGemini | E43: CapGemini | F43: Low | G43: Continue getting opportunities

Sheet Acct Goals  - Sample
B1: Account: | C1: <ACCOUNT NAME>
B2: Link to Acct in CRM: | C2: <link>
B4: 2026 Revenue Target: | C4: 5000000 | D4: 2026 Revenue to Date: | E4: 4567878 | F4: Remaining to Target: | G4: =C4-E4 -> 432122 | H4: Last Updated: | I4: 45958
B6: GENERAL ACCOUNT INFORMATION
B7: Account or Prospect? | C7: Account | E7: Annual Revenue: | F7: $6B | H7: Number of Employees: | I7: 2700
B8: Customer Location: | C8: Madison, WI | E8: Enterprise (s)/Office(s): | F8: Chicago | H8: Industry: | I8: Insurance
B9: Lead Source: | C9: Previous Client at Previous Customer | E9: Initial Contract: | F9: 45483 | H9: Average Contract Duration: | I9: 6 months
B10: Active Consultants (#): | C10: 0 | E10: Peak Consultants (#): | F10: 8 | H10: Ave Project Gross Margin %: | I10: 0.42
B11: Services (Primary): | C11: App Dev, FrontEnd, PM/BA, UI/UX
B13: ACCOUNT OBJECTIVES (5 Minimum)
B14: Account Objective | F14: Status | G14: Actions Required to Achieve | J14: Completion Date
B15: 1. Expand beyond Data Logistics into a new business area | F15: In process | G15: Meeting with Michelle - Need introductions to Marcus
B16: 2. Continue to solidify relationships at multiple levels of the organization and in multiple areas | F16: In process | G16: Push for more time with Sruthi to see how we can help her in her new role.
B17: 3. Achieve anchor status and get to $1M in revenue | F17: Complete | J17: 2/2/8/25
B18: 4. Become a trusted partner where we are the default for future work | F18: Hold | G18: Data Logistics doesn't have a customer so work is on hold and we haven't moved into new areas
B19: 5. Get public case study approved by client | F19: In Process | G19: Amy / Adam to follow up with Patrick to get case study approved
B20: <Other Samples>
B21: •Raise Rates by 7% by End of Year
B22: •Increase Team size by 2 consultants by 30 June 2026
B23: •Expand into at least one additional economic buyer within the client by year end.
B24: •Add Global Delivery capability to our team without
B25: •Get public case study approved by client
B26: •Meet with 10 additional business units at Director level or higher
B27: •Increase Gross Margins from 36.8% to 40.0%
B28: •Double Team Size by End of year
B29: •Increase Account Score from 3.75 to 4.0
B31: KEY ACTIVITY METRICS (3 Minimum)
B32: Key Metric | F32: Influence (H/M/L) | G32: Actions Required to Achieve | J32: Due Date
B33: Complete meetings with 5 new WPS contacts | F33: In Process | G33: Met with Michelle for Testing, Andrew, Sruthi in her new role, need meetings with Rochelle and Marcus | J33: 46022
B34: Complete 10 in person meetings | F34: In Process | G34: 8 In person meetings completed | J34: 46022
B35: Client Review by internal 3rd party every 6 months (3 months for top 10 account) - REQUIRED | F35: In Process | G35: 3 QBRs completed (including Dave) for 2025 and one scheduled for Nov. | J35: 45991
B36: <Other Samples>
B37: •Meet with “Decision Maker” in person 6 times per year
B38: •Customer meetings per year
B39: •Client Review by internal 3rd Party Every Six Months, Every 3 months for a top 10 account (Required)
B40: •Consultant Reviews for every assigned consultant every 6 months (Required)
B42: PARTNERSHIP-RELATED ACTIVITIES
B43: Partnership | C43: Does Client have Tech? | D43: Rep Name | F43: Relationship w/ Rep | G43: Deals Registered? | H43: Actions | J43: Due Date
B44: AWS | C44: No
B45: Confluent | C45: No
B46: Databricks | C46: No | H46: Got rid of this
B47: Google | C47: No
B48: Microsoft | C48: Yes | D48: Alesh Bruenwald | F48: Strong | G48: 2 | H48: Working consistently with Alesha - scheduling meeting for Q4 to see status
B49: SAP | C49: No
B50: Snowflake | C50: No
B52: OFFERING-RELATED ACTIVITIES
B53: Offering | D53: Does this apply to Client? | F53: Have we discussed? | G53: Actions | J53: Due Date
B54: Code Explorer | D54: Yes | F54: Yes | G54: Performed Demo - Bruce and Patrick are discussing - need to push them on this | J54: 46053
B55: Platform Migration (AWS, GCP, Azure) | D55: Yes | F55: Yes | G55: May be considering outsourcing - need to get Bruce to discuss this in more detail | J55: 46053
B56: Data | D56: Yes | F56: Yes
B57: Global Delivery | D57: No | F57: Yes | G57: Cannot pursue this at this time due to Government contracts | J57: N/A
B58: Training | D58: Yes | F58: Yes | G58: Met with Don McGreal, but didn't move forward
B59: Managed Services | D59: TBD | F59: No | G59: Need to discuss with Bruce and Patrick - NTT Data may be moving in on this? | J59: 46053
B60: Cloud Service Provider | D60: TBD | F60: No | G60: Need to discuss with Bruce and Patrick - NTT Data may be moving in on this? | J60: 46053
B61: Application Service Provider | D61: TBD | F61: No | G61: Need to discuss with Bruce and Patrick - NTT Data may be moving in on this? | J61: 46053
B63: OTHER ACTIVITIES
B64: Activity | E64: Requires Asst From? | G64: Actions | J64: Due Date
B65: Follow up with Ashley/Maggie Q4 on customer experience / Transpformation work. | E65: N/A | G65: Do ongoing outreach | J65: 45962
B66: Understand what they were using Databricks for and is there a better solution to achieve the goal (Fabric?) | E66: N/A | G66: Follow up with Bruce and Patrick to gather more information | J66: 45962
B67: Get ECIF dollars for WPS - Pending first client signup | E67: N/A | G67: Pending first DL client - continue to meet with Alesha on this | J67: 46022
B68: Schedule PowerAutomate Workshop (pending AI hire) | E68: N/A | G68: Have done outreach - need to continue to follow up with Tony and Patrick | J68: 45976
B69: Meet with new Health Plan Leader | E69: N/A | G69: Need Bruce to provide introductions | J69: 46053
B70: Schedule AI CTO in Madison for WPS and Erdman | E70: N/A | G70: Get dates from Patrick and Bruce | J70: 45992
B73: COMPLETED ACTIVITIES
B74: Item | G74: Actions | J74: Completed Date
B75: Respond to RFP for IT Assessment | J75: 45520
B76: Follow up with Patrick on Data Logistics Portal | J76: 45518
B77: Set up meeting with Sruthi on testing to see what her goals are. (Done as part of DL project) | J77: 45601
B78: Complete MSA | J78: 45579
B79: Update proposal based on platform request | J79: 45566
B80: Send SOW for updated Discovery phase | J80: 45575
B81: Reach out to Thomas Cousins for MS Partner | J81: 45579
B82: SOW for Design / Implementation Phase provided and signed | J82: 45611
B83: Present proposal for SDLC design guidance & documentation for general and QA approaches - NO - See it as internal role. | J83: 45611
B84: In Person client visit to Madison by Amy (possibly others) week of Nov. 18th. Meet with CIO, Bruce Gray on status as well as future opportunities as well as others who might be in town - COMPLETED 12/10 | J84: 45618
B85: Establish Weekly Status Meeting - Fridays | J85: 45604
B86: Once Azure Admin, register streams - ?? May not be able to register as PAL or POC due to Gov't Tenent | J86: 45621
... B105: MS to Validate Architecture (pending more details) | J105: 45703

Sheet Acct Information - Sample
B1: GENERAL ACCOUNT INFORMATION
B2: Customer Name: | C2: ='Acct Goals - Sample'!C1 -> <ACCOUNT NAME> | E2: Account or Prospect | F2: ='Acct Goals - Sample'!C7 -> Account | H2: Last Updated | I2: ='Acct Goals - Sample'!I4 -> 45958
B3: KEY CONTACTS
B4: Name | D4: Title | F4: Influence (H/M/L) | G4: Relationship | H4: Actions / Notes
B5: Bruce Gray | D5: CIO | G5: Very strong | H5: Friendly to improving, definitely an ally, but will need to prove ourselves to him, especially in technical areas. May have to go to RFP for more things due to Gov't agency status. - Invited to Holiday Party, but cannot attend. Regroup in Jan 2026.
B6: Patrick Sim | D6: VP of Architecture | G6: Very strong | H6: Impressed with what he has seen thus far. Positive Feedback. Invited to holiday party. Working on Q4 in person meeting.
B7: Sruthi Gujjula | D7: Testing Lead | G7: Strong | H7: May have affiliations to other firms. Will likely defer to Patrick for buying decision. Doesn't know Improving's capabilities in this area.
B8: Dave Nagrocki | D8: Enterprise Architect | G8: Average | H8: Doesn't know us but participated in Logistics Portal technical discussions
B9: Sara Redford | D9: Vice President, Enterprise Risk & Business Solutions | G9: Limited | H9: Running IT Assessment RFP - unclear on her level of influence
B10: Jeff Baudhuin | D10: Sourcing Manager | G10: Strong | H10: Procurement person
B11: Steve Chamberlain | D11: Program Manager | G11: Very strong | H11: High trust with CIO, knows us from HCSC, has been an advocate so far
B12: Andrew McCready | D12: VP of Data Logistics | G12: Average | H12: Will need to keep happy on DL project
B13: Rochelle Myers | D13: Chief Growth Officer | G13: Limited | H13: New to Org - Bruce's Business Partner - her buy in is very important
B14: Tim Tumbleson | D14: Head of Technology and Product Delivery - Data Logistics | G14: Very strong | H14: Working closely with us on DL project, but can sometimes be a barrier to getting things done.
B15: Michelle Brud | D15: Head of Agile Transformation and PMO | G15: Limited | H15: Bruce sent her our way based on training info I sent - seems open to Training
B16: Ashley Lieser | D16: Innovation, Experience Design, and Product Strategy | G16: Limited | H16: New to us, but likes that we have paperwork in place
... B19: Tony Sebion | D19: Architect | G19: Strong | H19: Leading PowerAutomate initiatives, some AI?
B21: COMPETITORS
B22: Competitor | C22: Notes (Number of Consultants, Services, Rates, etc.)
B23: Behaim | C23: https://www.behaimits.com/ - Currently using for maintainance (not sure where in org), taking over Data Logistics maintenance at low cost (<$85/hr)
B24: Nvisia | C24: Known resources to CTO - competed for DL work. Have experience at WPS (unknown where or in what capacity). Slightly higher or comparable cost to us.
B25: Apex | C25: http://apexconsultingservices.us/ Was in cluded in DL selection but was highest cost. Does not appear that they currently work with WPS
B26: Ensono | C26: Using for Mainframe as a service and looking to move to Infrastructure as a Service. Should not be a competitor to us for our App Dev services. Confirmed with Sean Keighron (ex Axiom/Ensono)
B27: HubCity Media | C27: Authentication Company - relying on them to do our user authentication components. Potential for partnering/acquisition? Checking with Adam.
B31: CURRENT TECH STACK
B32: Type | C32: Existing Solution | E32: Vendor | F32: Satisfaction | G32: Actions
B33: Cloud Platform | C33: Azure | E33: Microsoft | F33: High | G33: Considering outsourcing - talking to Ensono
B34: ERP - Mainframe​
B35: Modern APIs​
B36: Data​
B37: AI Solutions | C37: None | G37: Performed Code Explorer Demo - need to follow up
B38: Development​ | E38: Beheim | F38: Med | G38: Low cost alternative as Data Logistics doesn't have budget
B39: Training/Coaching​ | C39: Agile | E39: Internal | F39: High | G39: Strong internal PMO run by Michelle - have had meetings with Don (they have collegues in common) - Michelle doesn't feel she needs help.
B40: Global Delivery | C40: None | E40: None | F40: N/A | G40: Cannot go off shore due to Government tenent and HIPAA constrainst at this time

Sheet Customer Profile
L31: ./
