Workbook

Sheet Dashboard
A1: 2026 REGIONAL DIRECTOR COMPENSATION TRACKER
A2: One Texas – David O'Hara | Version 2.1 | February 10, 2026
B4: COMPENSATION SUMMARY
B5: Base Salary | C5: 180000
B6: Component 1: Book of Business Bonus | C6: ='Comp 1 - BoB'!H38 -> -0.50082741
B7: Component 2: Regional Growth Bonus | C7: ='Comp 2 - Region'!G18 -> 0.48779084
B8: Component 3: Strategic Impact Bonus | C8: ='Comp 3 - Strategic'!D17 -> 0
B9: Commission Earnings (YTD) | C9: =Commissions!E28 -> 0
B10: TOTAL COMPENSATION (YTD) | C10: =SUM(C5:C9) -> 179999.99
B11: On-Target Earnings (OTE) | C11: =180000+100000 -> 280000 | D11: Base $180K + $100K Bonus OTE
B13: COMPONENT STATUS AT A GLANCE
B14: Component | C14: Target | D14: Actual YTD | E14: % to Target | F14: Status
B15: 1: Book of Business Growth | C15: ≥6% Growth @ 30% GM | D15: ='Comp 1 - BoB'!H36 -> 0 | E15: ='Comp 1 - BoB'!H37 -> 0 | F15: On Track
B16: 2: Regional Growth | C16: ≥6% Growth @ 30% GM | D16: ='Comp 2 - Region'!G16 -> 0 | E16: ='Comp 2 - Region'!G17 -> -0.52741348 | F16: On Track
B17: 3a: Strategic Partnerships/GMS | C17: $5,000 max | D17: ='Comp 3 - Strategic'!D9 -> 0 | E17: ='Comp 3 - Strategic'!D10 -> 0 | F17: On Track
B18: 3b: Exec Programs/Account Plans | C18: $5,000 max | D18: ='Comp 3 - Strategic'!D15 -> 0 | E18: ='Comp 3 - Strategic'!D16 -> 0 | F18: On Track
B20: KEY ASSUMPTIONS & THRESHOLDS
B21: Minimum 6% YoY growth required on EACH component for ANY bonus payout
B22: Minimum 30% Gross Margin required on revenue counted toward bonus
B23: Winnipeg revenue: EXCLUDED from One Texas (pending final confirmation)
B24: Canadian AT&T revenue: EXCLUDED from One Texas
B25: Constellation separated from Kimberly accounts
B26: Focused Accounts Baseline: $14M | Total 2025 WD Revenue: $72.2M
B27: Yellow cells = user inputs | Blue text = editable | Green = cross-sheet links

Sheet Comp 1 - BoB
A1: COMPONENT 1: BOOK OF BUSINESS — NAMED ACCOUNT GROWTH
A2: Threshold: 6% YoY Growth | 30% Gross Margin Minimum | Up to 20 Named Accounts
B4: Named Account | C4: 2024 Revenue | D4: 2025 Revenue | E4: 2026 Target | F4: 2026 Actual YTD | G4: Gross Margin % | H4: YoY Growth %
B5: 7-Eleven | C5: 498160 | D5: 476120 | F5: 249240 | G5: 0.25 | H5: =IF(D5=0,"-",IF(F5=0,"-",(F5-D5)/D5)) -> -0.47651852
B6: Charles Schwab & Co | C6: 657574 | D6: 925267 | F6: 338516 | G6: 0.21 | H6: =IF(D6=0,"-",IF(F6=0,"-",(F6-D6)/D6)) -> -0.63414236
B7: McKesson Corporation | C7: 2064868.3 | D7: 1093108.8 | F7: 559386 | G7: 0.39 | H7: =IF(D7=0,"-",IF(F7=0,"-",(F7-D7)/D7)) -> -0.48826136
B8: Wendy's International, LLC | C8: 6244286.3 | D8: 5024642 | F8: 2308168 | G8: 0.4 | H8: =IF(D8=0,"-",IF(F8=0,"-",(F8-D8)/D8)) -> -0.54063036
B9: Insperity Services, LP | C9: 30688.62 | D9: 32100 | F9: 161680 | G9: 0.25 | H9: =IF(D9=0,"-",IF(F9=0,"-",(F9-D9)/D9)) -> 4.0367601
B10: PriceSmart | C10: 0 | D10: 628655.41 | F10: 142502 | G10: 0.5 | H10: =IF(D10=0,"-",IF(F10=0,"-",(F10-D10)/D10)) -> -0.77332256
B11: Autodesk, Inc | C11: 1297839.4 | D11: 2760096.2 | F11: 1677276 | G11: 0.28 | H11: =IF(D11=0,"-",IF(F11=0,"-",(F11-D11)/D11)) -> -0.39231249
B12: Intuit, Inc | C12: 307204 | D12: 1004738 | F12: 532126 | G12: 0.26 | H12: =IF(D12=0,"-",IF(F12=0,"-",(F12-D12)/D12)) -> -0.47038332
B13: Siemens Industry, Inc. | C13: 402415.9 | D13: 659367.62 | F13: 364042 | G13: 0.29 | H13: =IF(D13=0,"-",IF(F13=0,"-",(F13-D13)/D13)) -> -0.44789221
B14: ORIX Corporation USA | C14: 1116829.3 | D14: 770198.75 | F14: 351793 | G14: 0.22 | H14: =IF(D14=0,"-",IF(F14=0,"-",(F14-D14)/D14)) -> -0.54324387
B15: AT&T Services, Inc. | C15: 72.92 | D15: 17325 | F15: 0 | H15: =IF(D15=0,"-",IF(F15=0,"-",(F15-D15)/D15)) -> -
B16: Constellation Energy | F16: 0 | H16: =IF(D16=0,"-",IF(F16=0,"-",(F16-D16)/D16)) -> -
B17: Marriott | F17: 0 | H17: =IF(D17=0,"-",IF(F17=0,"-",(F17-D17)/D17)) -> -
B18: Kirby Corp | F18: 0 | H18: =IF(D18=0,"-",IF(F18=0,"-",(F18-D18)/D18)) -> -
B19: Expedia | F19: 0 | H19: =IF(D19=0,"-",IF(F19=0,"-",(F19-D19)/D19)) -> -
B20: Massimo | F20: 0 | H20: =IF(D20=0,"-",IF(F20=0,"-",(F20-D20)/D20)) -> -
B21: CBRE | F21: 0 | H21: =IF(D21=0,"-",IF(F21=0,"-",(F21-D21)/D21)) -> -
B22: Tenet | F22: 0 | H22: =IF(D22=0,"-",IF(F22=0,"-",(F22-D22)/D22)) -> -
B23: Texas Instruments | F23: 0 | H23: =IF(D23=0,"-",IF(F23=0,"-",(F23-D23)/D23)) -> -
B24: Builders First Source | F24: 0 | H24: =IF(D24=0,"-",IF(F24=0,"-",(F24-D24)/D24)) -> -
B25: TOTALS | C25: =SUM(C5:C24) -> 12619939 | D25: =SUM(D5:D24) -> 13391619 | E25: =SUM(E5:E24) -> 0 | F25: =SUM(F5:F24) -> 6684729 | G25: =IF(F25=0,"-",SUMPRODUCT(F5:F24,G5:G24)/F25) -> 0.32573554 | H25: =IF(D25=0,"-",(F25-D25)/D25) -> -0.50082741
B28: MONTHLY REVENUE TRACKING — BOOK OF BUSINESS
B29: Metric | D29: Jan | E29: Feb | F29: Mar | G29: Apr | H29: May | I29: Jun | J29: Jul | K29: Aug | L29: Sep | M29: Oct | N29: Nov | O29: Dec | P29: YTD Total
B30: BoB Revenue | P30: =SUM(C30:N30) -> 0
B31: BoB Cost | P31: =SUM(C31:N31) -> 0
B32: BoB Gross Profit | D32: =C30-C31 -> 0 | E32: =D30-D31 -> 0 | F32: =E30-E31 -> 0 | G32: =F30-F31 -> 0 | H32: =G30-G31 -> 0 | I32: =H30-H31 -> 0 | J32: =I30-I31 -> 0 | K32: =J30-J31 -> 0 | ... P32: =O30-O31 -> 0
B33: BoB Gross Margin % | D33: =IF(C30=0,"-",C32/C30) -> - | E33: =IF(D30=0,"-",D32/D30) -> - | F33: =IF(E30=0,"-",E32/E30) -> - | G33: =IF(F30=0,"-",F32/F30) -> - | H33: =IF(G30=0,"-",G32/G30) -> - | I33: =IF(H30=0,"-",H32/H30) -> - | J33: =IF(I30=0,"-",I32/I30) -> - | K33: =IF(J30=0,"-",J32/J30) -> - | ... P33: =IF(O30=0,"-",O32/O30) -> -
B34: Cumulative Revenue | D34: =C30 -> 0 | E34: =C34+D30 -> 0 | F34: =D34+E30 -> 0 | G34: =E34+F30 -> 0 | H34: =F34+G30 -> 0 | I34: =G34+H30 -> 0 | J34: =H34+I30 -> 0 | K34: =I34+J30 -> 0 | L34: =J34+K30 -> 0 | ... O34: =M34+N30 -> 0 | P34: =O30 -> 0
B35: Cumulative Growth %
B37: BONUS QUALIFICATION
B38: YoY BoB Growth % | H38: =H25 -> -0.50082741
B39: Weighted Avg GM % | H39: =G25 -> 0.32573554
B40: Bonus Earned (enter amount) | E40: Enter bonus per comp plan schedule | H40: 0

Sheet Comp 2 - Region
A1: COMPONENT 2: ONE TEXAS REGIONAL GROWTH
A2: Threshold: 6% YoY Growth | 30% Gross Margin Minimum | Excludes Winnipeg & Canadian AT&T
B4: 2025 One Texas Total Revenue | C4: 72200000
B5: 2025 Focused Accounts Baseline | C5: 14000000
B6: 6% Growth Target | C6: =C4*1.06 -> 76532000
B8: Metric | C8: Jan | D8: Feb | E8: Mar | F8: Apr | G8: May | H8: Jun | I8: Jul | J8: Aug | K8: Sep | L8: Oct | M8: Nov | N8: Dec | O8: YTD Total
B9: Regional Revenue | C9: 5440616 | D9: 5444848 | E9: 5865309 | F9: 5850646 | G9: 5273394 | H9: 6245934 | O9: =SUM(C9:N9) -> 34120747
B10: Regional Cost | C10: 3354802 | D10: 3378546 | E10: 3769893 | F10: 3695903 | G10: 3277815 | O10: =SUM(C10:N10) -> 17476959
B11: Regional Gross Profit | C11: =C9-C10 -> 2085814 | D11: =D9-D10 -> 2066302 | E11: =E9-E10 -> 2095416 | F11: =F9-F10 -> 2154743 | G11: =G9-G10 -> 1995579 | H11: =H9-H10 -> 6245934 | I11: =I9-I10 -> 0 | J11: =J9-J10 -> 0 | ... O11: =O9-O10 -> 16643788
B12: Regional GM % | C12: =IF(C9=0,"-",C11/C9) -> 0.38337828 | D12: =IF(D9=0,"-",D11/D9) -> 0.37949673 | E12: =IF(E9=0,"-",E11/E9) -> 0.35725586 | F12: =IF(F9=0,"-",F11/F9) -> 0.36829147 | G12: =IF(G9=0,"-",G11/G9) -> 0.37842403 | H12: =IF(H9=0,"-",H11/H9) -> 1 | I12: =IF(I9=0,"-",I11/I9) -> - | J12: =IF(J9=0,"-",J11/J9) -> - | ... O12: =IF(O9=0,"-",O11/O9) -> 0.48779084
B13: Cumulative Revenue | C13: =C9 -> 5440616 | D13: =C13+D9 -> 10885464 | E13: =D13+E9 -> 16750773 | F13: =E13+F9 -> 22601419 | G13: =F13+G9 -> 27874813 | H13: =G13+H9 -> 34120747 | I13: =H13+I9 -> 34120747 | J13: =I13+J9 -> 34120747 | K13: =J13+K9 -> 34120747 | ... O13: =N13+O9 -> 68241494
B14: Cumulative Growth vs 2025 | C14: =(C13-($C$4*(COLUMN()-2)/12))/($C$4*(COLUMN()-2)/12) -> -0.095742493 | D14: =(D13-($C$4*(COLUMN()-2)/12))/($C$4*(COLUMN()-2)/12) -> -0.095390803 | E14: =(E13-($C$4*(COLUMN()-2)/12))/($C$4*(COLUMN()-2)/12) -> -0.071979335 | F14: =(F13-($C$4*(COLUMN()-2)/12))/($C$4*(COLUMN()-2)/12) -> -0.060882867 | G14: =(G13-($C$4*(COLUMN()-2)/12))/($C$4*(COLUMN()-2)/12) -> -0.073413418 | H14: =(H13-($C$4*(COLUMN()-2)/12))/($C$4*(COLUMN()-2)/12) -> -0.054826953 | I14: =(I13-($C$4*(COLUMN()-2)/12))/($C$4*(COLUMN()-2)/12) -> -0.18985167 | J14: =(J13-($C$4*(COLUMN()-2)/12))/($C$4*(COLUMN()-2)/12) -> -0.29112021 | ... N14: =(N13-($C$4*(COLUMN()-2)/12))/($C$4*(COLUMN()-2)/12) -> -0.52741348 | O14: =IF($C$4=0,"-",(O13-$C$4)/$C$4) -> -0.054826953
B16: BONUS QUALIFICATION
B17: Regional YoY Growth % | G17: =IF(C4=0,"-",(O9-C4)/C4) -> -0.52741348
B18: Weighted Avg Regional GM % | G18: =IF(O9=0,"-",O11/O9) -> 0.48779084
B19: Bonus Earned (enter amount) | D19: Enter bonus per comp plan schedule | G19: 0

Sheet Comp 3 - Strategic
A1: COMPONENT 3: STRATEGIC IMPACT BONUS
A2: OTE: $10,000 Total | $2,500–$5,000 per item based on size of impact
B4: ITEM 1: STRATEGIC PARTNERSHIPS / GMS UTILIZATION
B5: Initiative / Activity | C5: Date | D5: Impact / Revenue Influence | E5: Notes
B10: Impact Assessment (put in a sentence) | D10: 0 | E10: $2,500 or $5,000 based on impact
B11: % to Max ($5,000) | D11: =IF(D10=0,0,D10/5000) -> 0
B12: ITEM 2: EXECUTIVE PROGRAMS / ACCOUNT PLAN ELEVATION
B13: Initiative / Activity | C13: Date | D13: Impact / Revenue Influence | E13: Notes
B16: Impact Assessment (put in a sentence) | D16: 0 | E16: $2,500 or $5,000 based on impact
B17: % to Max ($5,000) | D17: =IF(D16=0,0,D16/5000) -> 0
B19: TOTAL COMPONENT 3 BONUS | D19: =D10+D16 -> 0 | E19: Max $10,000

Sheet Commissions
A1: COMMISSION TRACKING
A2: Track commission-eligible deals and payouts
A3: Deal / Client
B4: Deal / Client | C4: Deal Value | D4: Commission Rate | E4: Commission Amt | F4: Date Closed | G4: Notes
E5: =IF(C5=0,"-",C5*D5) -> -
E6: =IF(C6=0,"-",C6*D6) -> -
E7: =IF(C7=0,"-",C7*D7) -> -
E8: =IF(C8=0,"-",C8*D8) -> -
E9: =IF(C9=0,"-",C9*D9) -> -
E10: =IF(C10=0,"-",C10*D10) -> -
E11: =IF(C11=0,"-",C11*D11) -> -
E12: =IF(C12=0,"-",C12*D12) -> -
E13: =IF(C13=0,"-",C13*D13) -> -
E14: =IF(C14=0,"-",C14*D14) -> -
E15: =IF(C15=0,"-",C15*D15) -> -
E16: =IF(C16=0,"-",C16*D16) -> -
... E27: =IF(C27=0,"-",C27*D27) -> -
B28: TOTAL COMMISSIONS YTD | E28: =SUM(E5:E27) -> 0

Sheet Leads
A1: LEADS PASSED
A2: Leads sourced and passed to sales team members
A4: Year | B4: Date | C4: Client | D4: Passed To
A5: 2025 | B5: 45771 | C5: Alcon | D5: ---
A6: 2025 | B6: 45834 | C6: Rayburn Electric | D6: Alexander Powell
A7: 2025 | B7: 45855 | C7: Signapay | D7: Craig Fisher
A8: 2025 | B8: 45898 | C8: Valley Forge | D8: Rod Patane
A9: 2025 | B9: 45904 | C9: Bridgepointe | D9: Mark Miesner
A10: 2025 | B10: 45915 | C10: Sports South | D10: Alexander Powell
A11: 2025 | B11: 45915 | C11: GTS Direct | D11: Mark Miesner
A12: 2025 | B12: 45960 | C12: Overwatch Rescue | D12: Mark Miesner
A13: 2025 | B13: 45960 | C13: DART | D13: Diana Stevens
A14: 2025 | B14: 45960 | C14: Bank of America | D14: Diana Stevens
A15: 2025 | B15: 45961 | C15: Evestnet | D15: Rod Patane
A16: 2025 | B16: 45964 | C16: Loomis | D16: Vicki Kelly
A17: 2025 | B17: 45965 | C17: AECom
A18: 2025 | B18: 45966 | C18: Bryson Washington | D18: Alexander Powell
A19: 2025 | B19: 45967 | C19: UMB | D19: Diana Stevens
A20: 2025 | B20: 45971 | C20: JPMorgan | D20: Diana Stevens
A21: 2025 | B21: 45973 | C21: Dallas College | D21: Alexander Powell
A22: 2025 | B22: 45979 | C22: WDG | D22: Rod Patane
A23: 2025 | B23: 45980 | C23: BOK | D23: Diana Stevens
A24: 2025 | B24: 45994 | C24: Capitalize Consulting | D24: Diana Stevens
A25: 2026 | B25: 46050 | C25: VestMed | D25: Stephen Johnson
A26: 2026 | B26: 46055 | C26: Veritas Financial Services | D26: Alexander Powell
A27: 2026 | B27: 46057 | C27: Integrated Financial Settlements
A28: 2026 | B28: 46066 | C28: Cardinal IT Solutions (Kashif) | D28: ---
A29: 2026 | B29: 46069 | C29: Steve Hall | D29: Derek Nwamadi
A30: 2026 | B30: 46070 | C30: Paragon Brokerage | D30: ---
A31: 2026 | B31: 46084 | C31: CBRE | D31: Me
A32: 2026 | B32: 46086 | C32: Kubota | D32: Diana Stevens
A33: 2026 | B33: 46093 | C33: Nexben | D33: Alexander Powell
A34: 2026 | B34: 46114 | C34: Specialty Capital | D34: Shalini Arora
A35: 2026 | B35: 46118 | C35: Birgo | D35: ---
A36: 2026 | B36: 46154 | C36: JSX | D36: Diana Stevens
A37: 2026 | B37: 46155 | C37: THL | D37: ---
A38: 2026 | B38: 46185 | C38: Spring Line Advisory | D38: ---
